clonearmy/__init__.py
clonearmy/cli.py
clonearmy/comparison.py
clonearmy/processor.py
clonearmy/report.py
clonearmy/utils.py
clonearmy-0.2.32.dist-info/METADATA
clonearmy-0.2.32.dist-info/WHEEL
clonearmy-0.2.32.dist-info/entry_points.txt
clonearmy-0.2.32.dist-info/RECORD
