Metadata-Version: 2.4
Name: clonearmy
Version: 0.2.32
Summary: Analyze haplotypes from Illumina paired-end amplicon sequencing
Project-URL: Documentation, https://github.com/username/clonearmy#readme
Project-URL: Source, https://github.com/username/clonearmy
Author-email: Jason D Limberis <Jason.Limberis@ucsf.edu>
License: MIT
Keywords: amplicon,bioinformatics,haplotype,sequencing
Classifier: Development Status :: 4 - Beta
Classifier: Intended Audience :: Science/Research
Classifier: License :: OSI Approved :: MIT License
Classifier: Programming Language :: Python :: 3
Classifier: Programming Language :: Python :: 3.8
Classifier: Programming Language :: Python :: 3.9
Classifier: Programming Language :: Python :: 3.10
Classifier: Programming Language :: Python :: 3.11
Classifier: Topic :: Scientific/Engineering :: Bio-Informatics
Requires-Python: >=3.8
Requires-Dist: biopython>=1.81
Requires-Dist: click>=8.1.0
Requires-Dist: jinja2>=3.1.0
Requires-Dist: matplotlib>=3.8.0
Requires-Dist: networkx>=3.2.0
Requires-Dist: numpy>=1.24.0
Requires-Dist: pandas>=2.1.0
Requires-Dist: plotly>=5.18.0
Requires-Dist: pyranges>=0.0.129
Requires-Dist: pysam>=0.22.0
Requires-Dist: rich>=13.7.0
Requires-Dist: scipy>=1.11.0
Requires-Dist: seaborn>=0.13.0
Requires-Dist: statsmodels
Requires-Dist: tqdm>=4.66.0
